meal_generator/__init__.py
meal_generator/generator.py
meal_generator/mappable.py
meal_generator/meal.py
meal_generator/meal_component.py
meal_generator/models.py
meal_generator/nutrient_profile.py
meal_generator/prompts.py
meal_generator/retriever.py
meal_generator-2.1.4.dist-info/METADATA
meal_generator-2.1.4.dist-info/WHEEL
meal_generator-2.1.4.dist-info/licenses/LICENSE
meal_generator-2.1.4.dist-info/RECORD
