Metadata-Version: 2.4
Name: meal-generator
Version: 2.1.4
Summary: A Python package to generate detailed meal information from natural language descriptions using Generative AI
Project-URL: Homepage, https://github.com/TomMcKenna1/meal-generator
Project-URL: Issues, https://github.com/TomMcKenna1/meal-generator/issues
Author-email: Tom McKenna <tom2mckenna@gmail.com>
License-Expression: MIT
License-File: LICENSE
Classifier: Operating System :: OS Independent
Classifier: Programming Language :: Python :: 3
Requires-Python: >=3.9
Requires-Dist: aiohttp
Requires-Dist: google-genai
Requires-Dist: pydantic
Provides-Extra: docs
Requires-Dist: sphinx; extra == 'docs'
Provides-Extra: test
Requires-Dist: pytest; extra == 'test'
Requires-Dist: pytest-asyncio; extra == 'test'
Requires-Dist: pytest-cov; extra == 'test'
